Metadata-Version: 1.1
Name: pas.plugins.sqlalchemy
Version: 0.4.2
Summary: SQLAlchemy-based PAS user/group/prop store.
Home-page: UNKNOWN
Author: Malthe Borch and Stefan Eletzhofer
Author-email: product-developers@lists.plone.org
License: GNU GPL v2
Keywords: web pas plone
Platform: UNKNOWN
Classifier: Development Status :: 3 - Alpha
Classifier: Intended Audience :: Developers
Classifier: Programming Language :: Python
Classifier: Topic :: Internet :: WWW/HTTP
Classifier: Topic :: Internet :: WWW/HTTP :: WSGI
Classifier: Topic :: Internet :: WWW/HTTP :: WSGI :: Application
